pymp4/__init__.py
pymp4/cli.py
pymp4/exceptions.py
pymp4/parser.py
pymp4/util.py
pymp4/tools/__init__.py
pymp4-1.3.2.dist-info/LICENSE
pymp4-1.3.2.dist-info/METADATA
pymp4-1.3.2.dist-info/WHEEL
pymp4-1.3.2.dist-info/entry_points.txt
pymp4-1.3.2.dist-info/top_level.txt
pymp4-1.3.2.dist-info/RECORD
