Metadata-Version: 2.1
Name: pymp4
Version: 1.3.2
Summary: A Python parser for MP4 boxes
Home-page: https://github.com/beardypig/pymp4
Author: beardypig
Author-email: git@beardypig.com
License: Apache 2.0
Classifier: Development Status :: 4 - Beta
Classifier: Environment :: Console
Classifier: Operating System :: POSIX
Classifier: Programming Language :: Python :: 2.7
Classifier: Programming Language :: Python :: 3.3
Classifier: Programming Language :: Python :: 3.4
Classifier: Programming Language :: Python :: 3.5
Classifier: Programming Language :: Python :: 3.6
Classifier: Topic :: Multimedia :: Sound/Audio
Classifier: Topic :: Multimedia :: Video
Classifier: Topic :: Utilities
License-File: LICENSE
Requires-Dist: construct (==2.8.8)
